sstc_schemas/__init__.py
sstc_schemas/schemas/__init__.py
sstc_schemas/schemas/sites_acronyms.yaml
sstc_schemas/version.py
sstc_schemas-0.1.3.dist-info/METADATA
sstc_schemas-0.1.3.dist-info/WHEEL
sstc_schemas-0.1.3.dist-info/RECORD
